{
  "frames": {
    "burger_8": {
      "frame": {
        "x": 0,
        "y": 0,
        "w": 88,
        "h": 16
      },
      "rotated": false,
      "trimmed": true,
      "spriteSourceSize": {
        "x": 4,
        "y": 48,
        "w": 88,
        "h": 16
      },
      "sourceSize": {
        "w": 96,
        "h": 112
      },
      "pivot": {
        "x": 0.5,
        "y": 0.5
      }
    },
    "burger_12": {
      "frame": {
        "x": 88,
        "y": 0,
        "w": 86,
        "h": 34
      },
      "rotated": false,
      "trimmed": true,
      "spriteSourceSize": {
        "x": 5,
        "y": 39,
        "w": 86,
        "h": 34
      },
      "sourceSize": {
        "w": 96,
        "h": 112
      },
      "pivot": {
        "x": 0.5,
        "y": 0.5
      }
    },
    "burger_4": {
      "frame": {
        "x": 0,
        "y": 16,
        "w": 86,
        "h": 34
      },
      "rotated": false,
      "trimmed": true,
      "spriteSourceSize": {
        "x": 5,
        "y": 39,
        "w": 86,
        "h": 34
      },
      "sourceSize": {
        "w": 96,
        "h": 112
      },
      "pivot": {
        "x": 0.5,
        "y": 0.5
      }
    },
    "burger_11": {
      "frame": {
        "x": 174,
        "y": 0,
        "w": 86,
        "h": 20
      },
      "rotated": false,
      "trimmed": true,
      "spriteSourceSize": {
        "x": 5,
        "y": 46,
        "w": 86,
        "h": 20
      },
      "sourceSize": {
        "w": 96,
        "h": 112
      },
      "pivot": {
        "x": 0.5,
        "y": 0.5
      }
    },
    "burger_5": {
      "frame": {
        "x": 260,
        "y": 0,
        "w": 86,
        "h": 20
      },
      "rotated": false,
      "trimmed": true,
      "spriteSourceSize": {
        "x": 5,
        "y": 46,
        "w": 86,
        "h": 20
      },
      "sourceSize": {
        "w": 96,
        "h": 112
      },
      "pivot": {
        "x": 0.5,
        "y": 0.5
      }
    },
    "burger_10": {
      "frame": {
        "x": 346,
        "y": 0,
        "w": 86,
        "h": 14
      },
      "rotated": false,
      "trimmed": true,
      "spriteSourceSize": {
        "x": 5,
        "y": 49,
        "w": 86,
        "h": 14
      },
      "sourceSize": {
        "w": 96,
        "h": 112
      },
      "pivot": {
        "x": 0.5,
        "y": 0.5
      }
    },
    "burger_6": {
      "frame": {
        "x": 432,
        "y": 0,
        "w": 86,
        "h": 14
      },
      "rotated": false,
      "trimmed": true,
      "spriteSourceSize": {
        "x": 5,
        "y": 49,
        "w": 86,
        "h": 14
      },
      "sourceSize": {
        "w": 96,
        "h": 112
      },
      "pivot": {
        "x": 0.5,
        "y": 0.5
      }
    },
    "burger_7": {
      "frame": {
        "x": 518,
        "y": 0,
        "w": 86,
        "h": 14
      },
      "rotated": false,
      "trimmed": true,
      "spriteSourceSize": {
        "x": 5,
        "y": 49,
        "w": 86,
        "h": 14
      },
      "sourceSize": {
        "w": 96,
        "h": 112
      },
      "pivot": {
        "x": 0.5,
        "y": 0.5
      }
    },
    "burger_13": {
      "frame": {
        "x": 604,
        "y": 0,
        "w": 84,
        "h": 48
      },
      "rotated": false,
      "trimmed": true,
      "spriteSourceSize": {
        "x": 6,
        "y": 32,
        "w": 84,
        "h": 48
      },
      "sourceSize": {
        "w": 96,
        "h": 112
      },
      "pivot": {
        "x": 0.5,
        "y": 0.5
      }
    },
    "burger_3": {
      "frame": {
        "x": 346,
        "y": 14,
        "w": 84,
        "h": 48
      },
      "rotated": false,
      "trimmed": true,
      "spriteSourceSize": {
        "x": 6,
        "y": 32,
        "w": 84,
        "h": 48
      },
      "sourceSize": {
        "w": 96,
        "h": 112
      },
      "pivot": {
        "x": 0.5,
        "y": 0.5
      }
    },
    "burger_14": {
      "frame": {
        "x": 174,
        "y": 20,
        "w": 82,
        "h": 62
      },
      "rotated": false,
      "trimmed": true,
      "spriteSourceSize": {
        "x": 7,
        "y": 25,
        "w": 82,
        "h": 62
      },
      "sourceSize": {
        "w": 96,
        "h": 112
      },
      "pivot": {
        "x": 0.5,
        "y": 0.5
      }
    },
    "burger_2": {
      "frame": {
        "x": 86,
        "y": 48,
        "w": 82,
        "h": 62
      },
      "rotated": false,
      "trimmed": true,
      "spriteSourceSize": {
        "x": 7,
        "y": 25,
        "w": 82,
        "h": 62
      },
      "sourceSize": {
        "w": 96,
        "h": 112
      },
      "pivot": {
        "x": 0.5,
        "y": 0.5
      }
    },
    "burger_1": {
      "frame": {
        "x": 0,
        "y": 50,
        "w": 80,
        "h": 80
      },
      "rotated": false,
      "trimmed": true,
      "spriteSourceSize": {
        "x": 8,
        "y": 16,
        "w": 80,
        "h": 80
      },
      "sourceSize": {
        "w": 96,
        "h": 112
      },
      "pivot": {
        "x": 0.5,
        "y": 0.5
      }
    },
    "burger_15": {
      "frame": {
        "x": 256,
        "y": 20,
        "w": 80,
        "h": 80
      },
      "rotated": false,
      "trimmed": true,
      "spriteSourceSize": {
        "x": 8,
        "y": 16,
        "w": 80,
        "h": 80
      },
      "sourceSize": {
        "w": 96,
        "h": 112
      },
      "pivot": {
        "x": 0.5,
        "y": 0.5
      }
    },
    "burger_9": {
      "frame": {
        "x": 518,
        "y": 0,
        "w": 86,
        "h": 14
      },
      "rotated": false,
      "trimmed": true,
      "spriteSourceSize": {
        "x": 5,
        "y": 49,
        "w": 86,
        "h": 14
      },
      "sourceSize": {
        "w": 96,
        "h": 112
      },
      "pivot": {
        "x": 0.5,
        "y": 0.5
      }
    }
  },
  "meta": {
    "app": "http://free-tex-packer.com",
    "version": "0.6.7",
    "image": "burger.png",
    "format": "RGBA8888",
    "size": {
      "w": 688,
      "h": 130
    },
    "scale": 1
  }
}